odoo8_addon_quality_control_force_valid-8.0.1.0.0-py2.7-nspkg.pth
odoo8_addon_quality_control_force_valid-8.0.1.0.0.dist-info/top_level.txt
odoo8_addon_quality_control_force_valid-8.0.1.0.0.dist-info/WHEEL
odoo8_addon_quality_control_force_valid-8.0.1.0.0.dist-info/RECORD
odoo8_addon_quality_control_force_valid-8.0.1.0.0.dist-info/metadata.json
odoo8_addon_quality_control_force_valid-8.0.1.0.0.dist-info/DESCRIPTION.rst
odoo8_addon_quality_control_force_valid-8.0.1.0.0.dist-info/METADATA
odoo8_addon_quality_control_force_valid-8.0.1.0.0.dist-info/namespace_packages.txt
odoo_addons/quality_control_force_valid/__openerp__.py
odoo_addons/quality_control_force_valid/__init__.py
odoo_addons/quality_control_force_valid/README.rst
odoo_addons/quality_control_force_valid/models/__init__.py
odoo_addons/quality_control_force_valid/models/qc_inspection.py
odoo_addons/quality_control_force_valid/i18n/es.po
odoo_addons/quality_control_force_valid/i18n/sl.po
odoo_addons/quality_control_force_valid/views/qc_inspection_view.xml
odoo_addons/quality_control_force_valid/tests/__init__.py
odoo_addons/quality_control_force_valid/tests/test_quality_control.py
odoo_addons/quality_control_force_valid/static/description/icon.png
